{
  "meta": {
    "tableName": "baseinfo_deploy_01KK47CNT2Y454Z33M0NKVTY2X",
    "fileName": "0160_INST_基本情報_20260302_01.xlsx",
    "sheetName": "INST_基本情報 (3)",
    "rowCount": 250,
    "importedAt": "2026-03-07T13:22:14.421Z"
  },
  "data": [
    {
      "id": 1,
      "line_id": "01KK47CNT2Y454Z33M0NKVTY2X",
      "n_cat": "anchor",
      "u_cat": "root",
      "parent_id": null,
      "dep_id": [],
      "key": "root",
      "i_type": "direct",
      "f_type": "group",
      "value": "template"
    },
    {
      "id": 2,
      "line_id": "01KK47CNT2ZCR56MAWTJSEZAPD",
      "n_cat": "line",
      "u_cat": "config",
      "parent_id": "01KK47CNT2Y454Z33M0NKVTY2X",
      "dep_id": [],
      "key": "varName",
      "i_type": "direct",
      "f_type": "text",
      "value": "baseinfo"
    },
    {
      "id": 3,
      "line_id": "01KK47CNT3JB8AKM9JNXX0X4HW",
      "n_cat": "line",
      "u_cat": "display",
      "parent_id": "01KK47CNT2Y454Z33M0NKVTY2X",
      "dep_id": [],
      "key": "label",
      "i_type": "direct",
      "f_type": "text",
      "value": "基本情報"
    },
    {
      "id": 4,
      "line_id": "01KK47CNT3D6CB0DVJY5FTCAD6",
      "n_cat": "line",
      "u_cat": "config",
      "parent_id": "01KK47CNT2Y454Z33M0NKVTY2X",
      "dep_id": [],
      "key": "addBlock",
      "i_type": "direct",
      "f_type": "boolean",
      "value": ""
    },
    {
      "id": 5,
      "line_id": "01KK47CNTGSVQEPJ3GWGYJ8460",
      "n_cat": "line",
      "u_cat": "config",
      "parent_id": "01KK47CNT2Y454Z33M0NKVTY2X",
      "dep_id": [],
      "key": "addNode",
      "i_type": "direct",
      "f_type": "boolean",
      "value": ""
    },
    {
      "id": 6,
      "line_id": "01KK47CNTGQR1K0TSCXB2B7ET5",
      "n_cat": "line",
      "u_cat": "config",
      "parent_id": "01KK47CNT2Y454Z33M0NKVTY2X",
      "dep_id": [],
      "key": "cpyNode",
      "i_type": "direct",
      "f_type": "boolean",
      "value": ""
    },
    {
      "id": 7,
      "line_id": "01KK47CNTGZQVF3V7Z07YG9EXE",
      "n_cat": "line",
      "u_cat": "config",
      "parent_id": "01KK47CNT2Y454Z33M0NKVTY2X",
      "dep_id": [],
      "key": "cpyBlock",
      "i_type": "direct",
      "f_type": "boolean",
      "value": ""
    },
    {
      "id": 8,
      "line_id": "01KK47CNTH7MESYE9M5CQCH9FA",
      "n_cat": "line",
      "u_cat": "config",
      "parent_id": "01KK47CNT2Y454Z33M0NKVTY2X",
      "dep_id": [],
      "key": "nodeId",
      "i_type": "direct",
      "f_type": "text",
      "value": ""
    },
    {
      "id": 9,
      "line_id": "01KK47CNT3R2QXBHC053JEG8VN",
      "n_cat": "anchor",
      "u_cat": "button",
      "parent_id": "01KK47CNT2Y454Z33M0NKVTY2X",
      "dep_id": [],
      "key": "buttonEditModeBtn",
      "i_type": "direct",
      "f_type": "group",
      "value": ""
    },
    {
      "id": 10,
      "line_id": "01KK47CNT3F6YN7KFVGBAYP21H",
      "n_cat": "line",
      "u_cat": "config",
      "parent_id": "01KK47CNT3R2QXBHC053JEG8VN",
      "dep_id": [],
      "key": "varName",
      "i_type": "direct",
      "f_type": "text",
      "value": "editModeBtn"
    },
    {
      "id": 11,
      "line_id": "01KK47CNT3ZWS42XC0NN2593D7",
      "n_cat": "line",
      "u_cat": "display",
      "parent_id": "01KK47CNT3R2QXBHC053JEG8VN",
      "dep_id": [],
      "key": "label",
      "i_type": "direct",
      "f_type": "text",
      "value": "編集モード"
    },
    {
      "id": 12,
      "line_id": "01KK47CNT3BATKJF9VWKS6035G",
      "n_cat": "line",
      "u_cat": "display",
      "parent_id": "01KK47CNT3R2QXBHC053JEG8VN",
      "dep_id": [],
      "key": "icon",
      "i_type": "direct",
      "f_type": "text",
      "value": ""
    },
    {
      "id": 13,
      "line_id": "01KK47CNT3JSC5HWJ3REP204P2",
      "n_cat": "line",
      "u_cat": "feed",
      "parent_id": "01KK47CNT3R2QXBHC053JEG8VN",
      "dep_id": [],
      "key": "value",
      "i_type": "direct",
      "f_type": "text",
      "value": "編集モード"
    },
    {
      "id": 14,
      "line_id": "01KK47CNT32EKA444BX4H5E9XP",
      "n_cat": "line",
      "u_cat": "config",
      "parent_id": "01KK47CNT3R2QXBHC053JEG8VN",
      "dep_id": [],
      "key": "jointIds",
      "i_type": "direct",
      "f_type": "array",
      "value": "table: joint_struct_[rootId]|\r\nlineId: [lineId]|\r\nkey: value"
    },
    {
      "id": 15,
      "line_id": "01KK47CNT34DXJA3BGC60RD4SW",
      "n_cat": "anchor",
      "u_cat": "button",
      "parent_id": "01KK47CNT2Y454Z33M0NKVTY2X",
      "dep_id": [],
      "key": "buttonViewModeBtn",
      "i_type": "direct",
      "f_type": "group",
      "value": ""
    },
    {
      "id": 16,
      "line_id": "01KK47CNT3NC0A5MDZMMVZ46DY",
      "n_cat": "line",
      "u_cat": "config",
      "parent_id": "01KK47CNT34DXJA3BGC60RD4SW",
      "dep_id": [],
      "key": "varName",
      "i_type": "direct",
      "f_type": "text",
      "value": "viewModeBtn"
    },
    {
      "id": 17,
      "line_id": "01KK47CNT3FDE1G2JNVENXDYHA",
      "n_cat": "line",
      "u_cat": "display",
      "parent_id": "01KK47CNT34DXJA3BGC60RD4SW",
      "dep_id": [],
      "key": "label",
      "i_type": "direct",
      "f_type": "text",
      "value": "表示モード"
    },
    {
      "id": 18,
      "line_id": "01KK47CNT3X7JXDD5S75VYCS9H",
      "n_cat": "line",
      "u_cat": "display",
      "parent_id": "01KK47CNT34DXJA3BGC60RD4SW",
      "dep_id": [],
      "key": "icon",
      "i_type": "direct",
      "f_type": "text",
      "value": ""
    },
    {
      "id": 19,
      "line_id": "01KK47CNT302R9W8VWWYXEFQV1",
      "n_cat": "line",
      "u_cat": "feed",
      "parent_id": "01KK47CNT34DXJA3BGC60RD4SW",
      "dep_id": [],
      "key": "value",
      "i_type": "direct",
      "f_type": "text",
      "value": "表示モード"
    },
    {
      "id": 20,
      "line_id": "01KK47CNT3NNPAW3YW632SSADV",
      "n_cat": "line",
      "u_cat": "config",
      "parent_id": "01KK47CNT34DXJA3BGC60RD4SW",
      "dep_id": [],
      "key": "jointIds",
      "i_type": "direct",
      "f_type": "array",
      "value": "table: joint_struct_[rootId]|\r\nlineId: [lineId]|\r\nkey: value"
    },
    {
      "id": 21,
      "line_id": "01KK47CNT3EERBQTYH7ENFNBVS",
      "n_cat": "anchor",
      "u_cat": "section",
      "parent_id": "01KK47CNT2Y454Z33M0NKVTY2X",
      "dep_id": [],
      "key": "sectionBaseinfo",
      "i_type": "direct",
      "f_type": "group",
      "value": ""
    },
    {
      "id": 22,
      "line_id": "01KK47CNT3QVQEDPBPECTFW5D9",
      "n_cat": "line",
      "u_cat": "config",
      "parent_id": "01KK47CNT3EERBQTYH7ENFNBVS",
      "dep_id": [],
      "key": "varName",
      "i_type": "direct",
      "f_type": "text",
      "value": "baseinfo"
    },
    {
      "id": 23,
      "line_id": "01KK47CNT36Q8XRDDQDXFX5VGN",
      "n_cat": "line",
      "u_cat": "display",
      "parent_id": "01KK47CNT3EERBQTYH7ENFNBVS",
      "dep_id": [],
      "key": "label",
      "i_type": "direct",
      "f_type": "text",
      "value": "基本情報"
    },
    {
      "id": 24,
      "line_id": "01KK47CNT4R6XE33CKZJDCJEEA",
      "n_cat": "line",
      "u_cat": "config",
      "parent_id": "01KK47CNT3EERBQTYH7ENFNBVS",
      "dep_id": [],
      "key": "order",
      "i_type": "direct",
      "f_type": "number",
      "value": 1
    },
    {
      "id": 25,
      "line_id": "01KK47CNT4NP29VH0WRJFAGH6Y",
      "n_cat": "line",
      "u_cat": "config",
      "parent_id": "01KK47CNT3EERBQTYH7ENFNBVS",
      "dep_id": [],
      "key": "addBlock",
      "i_type": "direct",
      "f_type": "boolean",
      "value": ""
    },
    {
      "id": 26,
      "line_id": "01KK47CNT41FQGN7DDBFVS2S6Y",
      "n_cat": "line",
      "u_cat": "config",
      "parent_id": "01KK47CNT3EERBQTYH7ENFNBVS",
      "dep_id": [],
      "key": "cpyBlock",
      "i_type": "direct",
      "f_type": "boolean",
      "value": ""
    },
    {
      "id": 27,
      "line_id": "01KK47CNT45T4ZC1V5QTMCPYK3",
      "n_cat": "line",
      "u_cat": "config",
      "parent_id": "01KK47CNT3EERBQTYH7ENFNBVS",
      "dep_id": [],
      "key": "delBlock",
      "i_type": "direct",
      "f_type": "boolean",
      "value": ""
    },
    {
      "id": 28,
      "line_id": "01KK47CNT40WTV0NREGCVV49RF",
      "n_cat": "line",
      "u_cat": "config",
      "parent_id": "01KK47CNT3EERBQTYH7ENFNBVS",
      "dep_id": [],
      "key": "fold",
      "i_type": "direct",
      "f_type": "boolean",
      "value": ""
    },
    {
      "id": 29,
      "line_id": "01KK47CNT4KRSQ42R99TBHC8BR",
      "n_cat": "line",
      "u_cat": "config",
      "parent_id": "01KK47CNT3EERBQTYH7ENFNBVS",
      "dep_id": [],
      "key": "icon",
      "i_type": "direct",
      "f_type": "text",
      "value": ""
    },
    {
      "id": 30,
      "line_id": "01KK47CNT4RNFFJHCFE0TJCCHW",
      "n_cat": "anchor",
      "u_cat": "button",
      "parent_id": "01KK47CNT3EERBQTYH7ENFNBVS",
      "dep_id": [],
      "key": "buttonBulkUpdateBtn",
      "i_type": "direct",
      "f_type": "group",
      "value": ""
    },
    {
      "id": 31,
      "line_id": "01KK47CNT4NREJ6DWRFMXDWZK5",
      "n_cat": "line",
      "u_cat": "config",
      "parent_id": "01KK47CNT4RNFFJHCFE0TJCCHW",
      "dep_id": [],
      "key": "varName",
      "i_type": "direct",
      "f_type": "text",
      "value": "bulkUpdateBtn"
    },
    {
      "id": 32,
      "line_id": "01KK47CNT4C8S65N4XK7K9Q7F2",
      "n_cat": "line",
      "u_cat": "display",
      "parent_id": "01KK47CNT4RNFFJHCFE0TJCCHW",
      "dep_id": [],
      "key": "label",
      "i_type": "direct",
      "f_type": "text",
      "value": "一括更新"
    },
    {
      "id": 33,
      "line_id": "01KK47CNT4H9V74F5615T5S0YM",
      "n_cat": "line",
      "u_cat": "display",
      "parent_id": "01KK47CNT4RNFFJHCFE0TJCCHW",
      "dep_id": [],
      "key": "icon",
      "i_type": "direct",
      "f_type": "text",
      "value": ""
    },
    {
      "id": 34,
      "line_id": "01KK47CNT4BEYSAZJD3YND33N9",
      "n_cat": "line",
      "u_cat": "feed",
      "parent_id": "01KK47CNT4RNFFJHCFE0TJCCHW",
      "dep_id": [],
      "key": "value",
      "i_type": "direct",
      "f_type": "text",
      "value": "一括更新"
    },
    {
      "id": 35,
      "line_id": "01KK47CNT4K4QMBN2A45BJVZFB",
      "n_cat": "line",
      "u_cat": "config",
      "parent_id": "01KK47CNT4RNFFJHCFE0TJCCHW",
      "dep_id": [],
      "key": "jointIds",
      "i_type": "direct",
      "f_type": "array",
      "value": "table: joint_struct_[rootId]|\r\nlineId: [lineId]|\r\nkey: value"
    },
    {
      "id": 36,
      "line_id": "01KK47CNT4FR2CVEGER0RV2S6G",
      "n_cat": "anchor",
      "u_cat": "section",
      "parent_id": "01KK47CNT3EERBQTYH7ENFNBVS",
      "dep_id": [],
      "key": "sectionName",
      "i_type": "direct",
      "f_type": "group",
      "value": ""
    },
    {
      "id": 37,
      "line_id": "01KK47CNT4W6RYZ1H45AYG2C3J",
      "n_cat": "line",
      "u_cat": "config",
      "parent_id": "01KK47CNT4FR2CVEGER0RV2S6G",
      "dep_id": [],
      "key": "varName",
      "i_type": "direct",
      "f_type": "text",
      "value": "name"
    },
    {
      "id": 38,
      "line_id": "01KK47CNT4H4EA7PQ2WFAWASMD",
      "n_cat": "line",
      "u_cat": "display",
      "parent_id": "01KK47CNT4FR2CVEGER0RV2S6G",
      "dep_id": [],
      "key": "label",
      "i_type": "direct",
      "f_type": "text",
      "value": "名前"
    },
    {
      "id": 39,
      "line_id": "01KK47CNT4FEHJ1Y3T54NBTTQX",
      "n_cat": "line",
      "u_cat": "config",
      "parent_id": "01KK47CNT4FR2CVEGER0RV2S6G",
      "dep_id": [],
      "key": "order",
      "i_type": "direct",
      "f_type": "number",
      "value": 1
    },
    {
      "id": 40,
      "line_id": "01KK47CNT5C2SNM3JEDPHRPFZA",
      "n_cat": "line",
      "u_cat": "config",
      "parent_id": "01KK47CNT4FR2CVEGER0RV2S6G",
      "dep_id": [],
      "key": "addBlock",
      "i_type": "direct",
      "f_type": "boolean",
      "value": ""
    },
    {
      "id": 41,
      "line_id": "01KK47CNT5TTHMSBMW5CBPWFN9",
      "n_cat": "line",
      "u_cat": "config",
      "parent_id": "01KK47CNT4FR2CVEGER0RV2S6G",
      "dep_id": [],
      "key": "cpyBlock",
      "i_type": "direct",
      "f_type": "boolean",
      "value": ""
    },
    {
      "id": 42,
      "line_id": "01KK47CNT5XS871PJ5JKN1X2A0",
      "n_cat": "line",
      "u_cat": "config",
      "parent_id": "01KK47CNT4FR2CVEGER0RV2S6G",
      "dep_id": [],
      "key": "delBlock",
      "i_type": "direct",
      "f_type": "boolean",
      "value": ""
    },
    {
      "id": 43,
      "line_id": "01KK47CNT5NXR8BGX7GZKWHRXP",
      "n_cat": "line",
      "u_cat": "config",
      "parent_id": "01KK47CNT4FR2CVEGER0RV2S6G",
      "dep_id": [],
      "key": "fold",
      "i_type": "direct",
      "f_type": "boolean",
      "value": ""
    },
    {
      "id": 44,
      "line_id": "01KK47CNT5QPSFSH6QBS16MK03",
      "n_cat": "line",
      "u_cat": "config",
      "parent_id": "01KK47CNT4FR2CVEGER0RV2S6G",
      "dep_id": [],
      "key": "icon",
      "i_type": "direct",
      "f_type": "text",
      "value": ""
    },
    {
      "id": 45,
      "line_id": "01KK47CNT5HZ9648A40B95FR57",
      "n_cat": "anchor",
      "u_cat": "field",
      "parent_id": "01KK47CNT4FR2CVEGER0RV2S6G",
      "dep_id": [],
      "key": "fieldName",
      "i_type": "direct",
      "f_type": "group",
      "value": ""
    },
    {
      "id": 46,
      "line_id": "01KK47CNT59EZAW62QX8QWNM94",
      "n_cat": "line",
      "u_cat": "config",
      "parent_id": "01KK47CNT5HZ9648A40B95FR57",
      "dep_id": [],
      "key": "varName",
      "i_type": "direct",
      "f_type": "text",
      "value": "name"
    },
    {
      "id": 47,
      "line_id": "01KK47CNT51QJ39J8Z3CCDN53Y",
      "n_cat": "line",
      "u_cat": "display",
      "parent_id": "01KK47CNT5HZ9648A40B95FR57",
      "dep_id": [],
      "key": "label",
      "i_type": "direct",
      "f_type": "text",
      "value": "名前"
    },
    {
      "id": 48,
      "line_id": "01KK47CNT5VDAAYEVVQ23AWG26",
      "n_cat": "line",
      "u_cat": "config",
      "parent_id": "01KK47CNT5HZ9648A40B95FR57",
      "dep_id": [],
      "key": "order",
      "i_type": "direct",
      "f_type": "number",
      "value": 1
    },
    {
      "id": 49,
      "line_id": "01KK47CNT57VV7DQ6H48ECPBCC",
      "n_cat": "line",
      "u_cat": "config",
      "parent_id": "01KK47CNT5HZ9648A40B95FR57",
      "dep_id": [],
      "key": "addBlock",
      "i_type": "direct",
      "f_type": "boolean",
      "value": ""
    },
    {
      "id": 50,
      "line_id": "01KK47CNT52AY77RFMQRPC25GB",
      "n_cat": "line",
      "u_cat": "config",
      "parent_id": "01KK47CNT5HZ9648A40B95FR57",
      "dep_id": [],
      "key": "delBlock",
      "i_type": "direct",
      "f_type": "boolean",
      "value": ""
    },
    {
      "id": 51,
      "line_id": "01KK47CNT5ZTA5STX729333WPS",
      "n_cat": "line",
      "u_cat": "config",
      "parent_id": "01KK47CNT5HZ9648A40B95FR57",
      "dep_id": [],
      "key": "cpyBlock",
      "i_type": "direct",
      "f_type": "boolean",
      "value": ""
    },
    {
      "id": 52,
      "line_id": "01KK47CNT5J2PN946PPQ1P9ZVD",
      "n_cat": "line",
      "u_cat": "config",
      "parent_id": "01KK47CNT5HZ9648A40B95FR57",
      "dep_id": [],
      "key": "required",
      "i_type": "direct",
      "f_type": "boolean",
      "value": true
    },
    {
      "id": 53,
      "line_id": "01KK47CNT5ZBAZ8AWARV65XSM5",
      "n_cat": "line",
      "u_cat": "feed",
      "parent_id": "01KK47CNT5HZ9648A40B95FR57",
      "dep_id": [],
      "key": "hint",
      "i_type": "direct",
      "f_type": "text",
      "value": ""
    },
    {
      "id": 54,
      "line_id": "01KK47CNT5H0YBBB1KT5JPQT3Y",
      "n_cat": "line",
      "u_cat": "display",
      "parent_id": "01KK47CNT5HZ9648A40B95FR57",
      "dep_id": [],
      "key": "placeHolder",
      "i_type": "direct",
      "f_type": "text",
      "value": "名前を入力してください"
    },
    {
      "id": 55,
      "line_id": "01KK47CNT54GTJZKMACKEXNXXZ",
      "n_cat": "line",
      "u_cat": "display",
      "parent_id": "01KK47CNT5HZ9648A40B95FR57",
      "dep_id": [],
      "key": "icon",
      "i_type": "direct",
      "f_type": "fa-name",
      "value": ""
    },
    {
      "id": 56,
      "line_id": "01KK47CNT5N38D5KB5G41JYT8T",
      "n_cat": "line",
      "u_cat": "config",
      "parent_id": "01KK47CNT5HZ9648A40B95FR57",
      "dep_id": [],
      "key": "digest",
      "i_type": "direct",
      "f_type": "boolean",
      "value": true
    },
    {
      "id": 57,
      "line_id": "01KK47CNT58MZFMX2JF7A06EA4",
      "n_cat": "line",
      "u_cat": "feed",
      "parent_id": "01KK47CNT5HZ9648A40B95FR57",
      "dep_id": [],
      "key": "value",
      "i_type": "direct",
      "f_type": "text",
      "value": "飯島愛"
    },
    {
      "id": 58,
      "line_id": "01KK47CNT5PGKN49HGJTB1M9BE",
      "n_cat": "anchor",
      "u_cat": "button",
      "parent_id": null,
      "dep_id": [],
      "key": "buttonEditBtn",
      "i_type": "direct",
      "f_type": "group",
      "value": ""
    },
    {
      "id": 59,
      "line_id": "01KK47CNT6YJHTPVZRT01G32QW",
      "n_cat": "line",
      "u_cat": "config",
      "parent_id": "01KK47CNT5PGKN49HGJTB1M9BE",
      "dep_id": [],
      "key": "varName",
      "i_type": "direct",
      "f_type": "text",
      "value": "editBtn"
    },
    {
      "id": 60,
      "line_id": "01KK47CNT6G8Y7F4C5Z8T6NG41",
      "n_cat": "line",
      "u_cat": "display",
      "parent_id": "01KK47CNT5PGKN49HGJTB1M9BE",
      "dep_id": [],
      "key": "label",
      "i_type": "direct",
      "f_type": "text",
      "value": "編集"
    },
    {
      "id": 61,
      "line_id": "01KK47CNT6R432Q8FHMTJSG43H",
      "n_cat": "line",
      "u_cat": "display",
      "parent_id": "01KK47CNT5PGKN49HGJTB1M9BE",
      "dep_id": [],
      "key": "icon",
      "i_type": "direct",
      "f_type": "text",
      "value": ""
    },
    {
      "id": 62,
      "line_id": "01KK47CNT6QZM2YR6HHTZXNRKF",
      "n_cat": "line",
      "u_cat": "feed",
      "parent_id": "01KK47CNT5PGKN49HGJTB1M9BE",
      "dep_id": [],
      "key": "value",
      "i_type": "direct",
      "f_type": "text",
      "value": "編集"
    },
    {
      "id": 63,
      "line_id": "01KK47CNT6JCS2XERV5Z6XVGX5",
      "n_cat": "line",
      "u_cat": "config",
      "parent_id": "01KK47CNT5PGKN49HGJTB1M9BE",
      "dep_id": [],
      "key": "jointIds",
      "i_type": "direct",
      "f_type": "array",
      "value": "table: joint_struct_[rootId]|\r\nlineId: [lineId]|\r\nkey: value"
    },
    {
      "id": 64,
      "line_id": "01KK47CNT6GFWNWZNYTAH4X275",
      "n_cat": "anchor",
      "u_cat": "button",
      "parent_id": null,
      "dep_id": [],
      "key": "buttonUpdateBtn",
      "i_type": "direct",
      "f_type": "group",
      "value": ""
    },
    {
      "id": 65,
      "line_id": "01KK47CNT6V7CG55CV03E34FD4",
      "n_cat": "line",
      "u_cat": "config",
      "parent_id": "01KK47CNT6GFWNWZNYTAH4X275",
      "dep_id": [],
      "key": "varName",
      "i_type": "direct",
      "f_type": "text",
      "value": "updateBtn"
    },
    {
      "id": 66,
      "line_id": "01KK47CNT6PASQ9M1M06410PXN",
      "n_cat": "line",
      "u_cat": "display",
      "parent_id": "01KK47CNT6GFWNWZNYTAH4X275",
      "dep_id": [],
      "key": "label",
      "i_type": "direct",
      "f_type": "text",
      "value": "更新"
    },
    {
      "id": 67,
      "line_id": "01KK47CNT6XJEDSETV1DT2BF8H",
      "n_cat": "line",
      "u_cat": "display",
      "parent_id": "01KK47CNT6GFWNWZNYTAH4X275",
      "dep_id": [],
      "key": "icon",
      "i_type": "direct",
      "f_type": "text",
      "value": ""
    },
    {
      "id": 68,
      "line_id": "01KK47CNT69KTK3VF0X1PJ5CD7",
      "n_cat": "line",
      "u_cat": "feed",
      "parent_id": "01KK47CNT6GFWNWZNYTAH4X275",
      "dep_id": [],
      "key": "value",
      "i_type": "direct",
      "f_type": "text",
      "value": "更新"
    },
    {
      "id": 69,
      "line_id": "01KK47CNT6WBA10TXEQ91D5Q2R",
      "n_cat": "line",
      "u_cat": "config",
      "parent_id": "01KK47CNT6GFWNWZNYTAH4X275",
      "dep_id": [],
      "key": "jointIds",
      "i_type": "direct",
      "f_type": "array",
      "value": "table: joint_struct_[rootId]|\r\nlineId: [lineId]|\r\nkey: value"
    },
    {
      "id": 70,
      "line_id": "01KK47CNT6M7CGZW4MNCWBHNN4",
      "n_cat": "anchor",
      "u_cat": "button",
      "parent_id": null,
      "dep_id": [],
      "key": "buttonViewBtn",
      "i_type": "direct",
      "f_type": "group",
      "value": ""
    },
    {
      "id": 71,
      "line_id": "01KK47CNT6EEYAGHR5G5235KPM",
      "n_cat": "line",
      "u_cat": "config",
      "parent_id": "01KK47CNT6M7CGZW4MNCWBHNN4",
      "dep_id": [],
      "key": "varName",
      "i_type": "direct",
      "f_type": "text",
      "value": "viewBtn"
    },
    {
      "id": 72,
      "line_id": "01KK47CNT6FJ1MC1BQKCQMZZGP",
      "n_cat": "line",
      "u_cat": "display",
      "parent_id": "01KK47CNT6M7CGZW4MNCWBHNN4",
      "dep_id": [],
      "key": "label",
      "i_type": "direct",
      "f_type": "text",
      "value": "表示"
    },
    {
      "id": 73,
      "line_id": "01KK47CNT6GJ4P2E18Z96K52N4",
      "n_cat": "line",
      "u_cat": "display",
      "parent_id": "01KK47CNT6M7CGZW4MNCWBHNN4",
      "dep_id": [],
      "key": "icon",
      "i_type": "direct",
      "f_type": "text",
      "value": ""
    },
    {
      "id": 74,
      "line_id": "01KK47CNT68KY7ZB756PA7S894",
      "n_cat": "line",
      "u_cat": "feed",
      "parent_id": "01KK47CNT6M7CGZW4MNCWBHNN4",
      "dep_id": [],
      "key": "value",
      "i_type": "direct",
      "f_type": "text",
      "value": "表示"
    },
    {
      "id": 75,
      "line_id": "01KK47CNT6AN6SYCR3YFZKT6MG",
      "n_cat": "line",
      "u_cat": "config",
      "parent_id": "01KK47CNT6M7CGZW4MNCWBHNN4",
      "dep_id": [],
      "key": "jointIds",
      "i_type": "direct",
      "f_type": "array",
      "value": "table: joint_struct_[rootId]|\r\nlineId: [lineId]|\r\nkey: value"
    },
    {
      "id": 76,
      "line_id": "01KK47CNT7QRSCKDDG03502NVM",
      "n_cat": "anchor",
      "u_cat": "section",
      "parent_id": "01KK47CNT3EERBQTYH7ENFNBVS",
      "dep_id": [],
      "key": "sectionGender",
      "i_type": "direct",
      "f_type": "group",
      "value": ""
    },
    {
      "id": 77,
      "line_id": "01KK47CNT77YCNZNYY2Z4HD449",
      "n_cat": "line",
      "u_cat": "config",
      "parent_id": "01KK47CNT7QRSCKDDG03502NVM",
      "dep_id": [],
      "key": "varName",
      "i_type": "direct",
      "f_type": "text",
      "value": "gender"
    },
    {
      "id": 78,
      "line_id": "01KK47CNT7KJ8D20VZR4CQA8MS",
      "n_cat": "line",
      "u_cat": "display",
      "parent_id": "01KK47CNT7QRSCKDDG03502NVM",
      "dep_id": [],
      "key": "label",
      "i_type": "direct",
      "f_type": "text",
      "value": "性別"
    },
    {
      "id": 79,
      "line_id": "01KK47CNT76N1T5Y4YQA0GA9ZN",
      "n_cat": "line",
      "u_cat": "config",
      "parent_id": "01KK47CNT7QRSCKDDG03502NVM",
      "dep_id": [],
      "key": "order",
      "i_type": "direct",
      "f_type": "number",
      "value": 2
    },
    {
      "id": 80,
      "line_id": "01KK47CNT74V2HJAB7ENXWZFAH",
      "n_cat": "line",
      "u_cat": "config",
      "parent_id": "01KK47CNT7QRSCKDDG03502NVM",
      "dep_id": [],
      "key": "addBlock",
      "i_type": "direct",
      "f_type": "boolean",
      "value": ""
    },
    {
      "id": 81,
      "line_id": "01KK47CNT78QS492Q2C0XJM2W0",
      "n_cat": "line",
      "u_cat": "config",
      "parent_id": "01KK47CNT7QRSCKDDG03502NVM",
      "dep_id": [],
      "key": "cpyBlock",
      "i_type": "direct",
      "f_type": "boolean",
      "value": ""
    },
    {
      "id": 82,
      "line_id": "01KK47CNT7NYQGGM3FKX464GBV",
      "n_cat": "line",
      "u_cat": "config",
      "parent_id": "01KK47CNT7QRSCKDDG03502NVM",
      "dep_id": [],
      "key": "delBlock",
      "i_type": "direct",
      "f_type": "boolean",
      "value": ""
    },
    {
      "id": 83,
      "line_id": "01KK47CNT7R1T7N2JB3NB2KTAV",
      "n_cat": "line",
      "u_cat": "config",
      "parent_id": "01KK47CNT7QRSCKDDG03502NVM",
      "dep_id": [],
      "key": "fold",
      "i_type": "direct",
      "f_type": "boolean",
      "value": ""
    },
    {
      "id": 84,
      "line_id": "01KK47CNT7QWBNFTHBC92GGP5F",
      "n_cat": "line",
      "u_cat": "config",
      "parent_id": "01KK47CNT7QRSCKDDG03502NVM",
      "dep_id": [],
      "key": "icon",
      "i_type": "direct",
      "f_type": "text",
      "value": ""
    },
    {
      "id": 85,
      "line_id": "01KK47CNT7MY2PJQB9SQDT5CS5",
      "n_cat": "anchor",
      "u_cat": "field",
      "parent_id": "01KK47CNT7QRSCKDDG03502NVM",
      "dep_id": [],
      "key": "fieldGender",
      "i_type": "direct",
      "f_type": "group",
      "value": ""
    },
    {
      "id": 86,
      "line_id": "01KK47CNT70DETD3G1D30C2XRQ",
      "n_cat": "line",
      "u_cat": "config",
      "parent_id": "01KK47CNT7MY2PJQB9SQDT5CS5",
      "dep_id": [],
      "key": "varName",
      "i_type": "direct",
      "f_type": "text",
      "value": "gender"
    },
    {
      "id": 87,
      "line_id": "01KK47CNT7F00V7FRH6C9ZAGFC",
      "n_cat": "line",
      "u_cat": "display",
      "parent_id": "01KK47CNT7MY2PJQB9SQDT5CS5",
      "dep_id": [],
      "key": "label",
      "i_type": "direct",
      "f_type": "text",
      "value": "性別"
    },
    {
      "id": 88,
      "line_id": "01KK47CNT7RWDZ9CE03BKHCC0X",
      "n_cat": "line",
      "u_cat": "config",
      "parent_id": "01KK47CNT7MY2PJQB9SQDT5CS5",
      "dep_id": [],
      "key": "order",
      "i_type": "direct",
      "f_type": "number",
      "value": 1
    },
    {
      "id": 89,
      "line_id": "01KK47CNT72FDH9T29PSY25XPV",
      "n_cat": "line",
      "u_cat": "config",
      "parent_id": "01KK47CNT7MY2PJQB9SQDT5CS5",
      "dep_id": [],
      "key": "addBlock",
      "i_type": "direct",
      "f_type": "boolean",
      "value": ""
    },
    {
      "id": 90,
      "line_id": "01KK47CNT76Q3KP97KNTDX8ZKW",
      "n_cat": "line",
      "u_cat": "config",
      "parent_id": "01KK47CNT7MY2PJQB9SQDT5CS5",
      "dep_id": [],
      "key": "delBlock",
      "i_type": "direct",
      "f_type": "boolean",
      "value": ""
    },
    {
      "id": 91,
      "line_id": "01KK47CNT7EX72ZR1980A9KGK5",
      "n_cat": "line",
      "u_cat": "config",
      "parent_id": "01KK47CNT7MY2PJQB9SQDT5CS5",
      "dep_id": [],
      "key": "cpyBlock",
      "i_type": "direct",
      "f_type": "boolean",
      "value": ""
    },
    {
      "id": 92,
      "line_id": "01KK47CNT77XQGHRHZ8ZX85A3D",
      "n_cat": "line",
      "u_cat": "config",
      "parent_id": "01KK47CNT7MY2PJQB9SQDT5CS5",
      "dep_id": [],
      "key": "required",
      "i_type": "direct",
      "f_type": "boolean",
      "value": ""
    },
    {
      "id": 93,
      "line_id": "01KK47CNT7PSFP112YNTP68VTK",
      "n_cat": "line",
      "u_cat": "feed",
      "parent_id": "01KK47CNT7MY2PJQB9SQDT5CS5",
      "dep_id": [],
      "key": "hint",
      "i_type": "direct",
      "f_type": "text",
      "value": ""
    },
    {
      "id": 94,
      "line_id": "01KK47CNT8HJ9FFC6ATJFEEBKJ",
      "n_cat": "line",
      "u_cat": "display",
      "parent_id": "01KK47CNT7MY2PJQB9SQDT5CS5",
      "dep_id": [],
      "key": "placeHolder",
      "i_type": "direct",
      "f_type": "text",
      "value": "性別を選択してください"
    },
    {
      "id": 95,
      "line_id": "01KK47CNT8F31391FT67XFPEEE",
      "n_cat": "line",
      "u_cat": "display",
      "parent_id": "01KK47CNT7MY2PJQB9SQDT5CS5",
      "dep_id": [],
      "key": "icon",
      "i_type": "direct",
      "f_type": "fa-name",
      "value": ""
    },
    {
      "id": 96,
      "line_id": "01KK47CNT8XYZQM8P1TZQ1PAKN",
      "n_cat": "line",
      "u_cat": "config",
      "parent_id": "01KK47CNT7MY2PJQB9SQDT5CS5",
      "dep_id": [],
      "key": "digest",
      "i_type": "direct",
      "f_type": "boolean",
      "value": true
    },
    {
      "id": 97,
      "line_id": "01KK47CNT8BZHS7ZH1KKS8ET4M",
      "n_cat": "line",
      "u_cat": "feed",
      "parent_id": "01KK47CNT7MY2PJQB9SQDT5CS5",
      "dep_id": [],
      "key": "value",
      "i_type": "direct",
      "f_type": "select",
      "value": "女性"
    },
    {
      "id": 98,
      "line_id": "01KK47CNT8Z8PMEE8AAFTBFQZD",
      "n_cat": "anchor",
      "u_cat": "option",
      "parent_id": "01KK47CNT8BZHS7ZH1KKS8ET4M",
      "dep_id": [],
      "key": "optionGender",
      "i_type": "direct",
      "f_type": "group",
      "value": ""
    },
    {
      "id": 99,
      "line_id": "01KK47CNT8SFJWHNWPQ25YYZEM",
      "n_cat": "line",
      "u_cat": "config",
      "parent_id": "01KK47CNT8Z8PMEE8AAFTBFQZD",
      "dep_id": [],
      "key": "varName",
      "i_type": "direct",
      "f_type": "text",
      "value": "gender"
    },
    {
      "id": 100,
      "line_id": "01KK47CNT8MFB4XWX1B97FJXAF",
      "n_cat": "line",
      "u_cat": "display",
      "parent_id": "01KK47CNT8Z8PMEE8AAFTBFQZD",
      "dep_id": [],
      "key": "display",
      "i_type": "direct",
      "f_type": "text",
      "value": "normal"
    },
    {
      "id": 101,
      "line_id": "01KK47CNT8QYP7BZGHNSBQJQZJ",
      "n_cat": "line",
      "u_cat": "config",
      "parent_id": "01KK47CNT8Z8PMEE8AAFTBFQZD",
      "dep_id": [],
      "key": "tableId",
      "i_type": "direct",
      "f_type": "text",
      "value": ""
    },
    {
      "id": 102,
      "line_id": "01KK47CNT8EXFNWGCBKTZ0VYW3",
      "n_cat": "line",
      "u_cat": "config",
      "parent_id": "01KK47CNT8Z8PMEE8AAFTBFQZD",
      "dep_id": [],
      "key": "value",
      "i_type": "direct",
      "f_type": "array",
      "value": "[男性,女性,その他]"
    },
    {
      "id": 103,
      "line_id": "01KK47CNT8TENTS25RG4WM880B",
      "n_cat": "anchor",
      "u_cat": "section",
      "parent_id": "01KK47CNT3EERBQTYH7ENFNBVS",
      "dep_id": [],
      "key": "sectionAddress",
      "i_type": "direct",
      "f_type": "group",
      "value": ""
    },
    {
      "id": 104,
      "line_id": "01KK47CNT8X80V2GZFPWNQWMAQ",
      "n_cat": "line",
      "u_cat": "config",
      "parent_id": "01KK47CNT8TENTS25RG4WM880B",
      "dep_id": [],
      "key": "varName",
      "i_type": "direct",
      "f_type": "text",
      "value": "address"
    },
    {
      "id": 105,
      "line_id": "01KK47CNT8CX4FAARW1ZKZ1479",
      "n_cat": "line",
      "u_cat": "display",
      "parent_id": "01KK47CNT8TENTS25RG4WM880B",
      "dep_id": [],
      "key": "label",
      "i_type": "direct",
      "f_type": "text",
      "value": "現住所"
    },
    {
      "id": 106,
      "line_id": "01KK47CNT8AY7QCZ9VSRJ27ZMF",
      "n_cat": "line",
      "u_cat": "config",
      "parent_id": "01KK47CNT8TENTS25RG4WM880B",
      "dep_id": [],
      "key": "order",
      "i_type": "direct",
      "f_type": "number",
      "value": 3
    },
    {
      "id": 107,
      "line_id": "01KK47CNT85AHEBFYESVYYRAPZ",
      "n_cat": "line",
      "u_cat": "config",
      "parent_id": "01KK47CNT8TENTS25RG4WM880B",
      "dep_id": [],
      "key": "addBlock",
      "i_type": "direct",
      "f_type": "boolean",
      "value": ""
    },
    {
      "id": 108,
      "line_id": "01KK47CNT8B2FF1ZBPA68VWKBE",
      "n_cat": "line",
      "u_cat": "config",
      "parent_id": "01KK47CNT8TENTS25RG4WM880B",
      "dep_id": [],
      "key": "cpyBlock",
      "i_type": "direct",
      "f_type": "boolean",
      "value": ""
    },
    {
      "id": 109,
      "line_id": "01KK47CNT828WJMQVRFXRNGQZP",
      "n_cat": "line",
      "u_cat": "config",
      "parent_id": "01KK47CNT8TENTS25RG4WM880B",
      "dep_id": [],
      "key": "delBlock",
      "i_type": "direct",
      "f_type": "boolean",
      "value": ""
    },
    {
      "id": 110,
      "line_id": "01KK47CNT8JXCP7523Q68R1V9F",
      "n_cat": "line",
      "u_cat": "config",
      "parent_id": "01KK47CNT8TENTS25RG4WM880B",
      "dep_id": [],
      "key": "fold",
      "i_type": "direct",
      "f_type": "boolean",
      "value": ""
    },
    {
      "id": 111,
      "line_id": "01KK47CNT85HCNW5HMF9BTK1QF",
      "n_cat": "line",
      "u_cat": "config",
      "parent_id": "01KK47CNT8TENTS25RG4WM880B",
      "dep_id": [],
      "key": "icon",
      "i_type": "direct",
      "f_type": "text",
      "value": ""
    },
    {
      "id": 112,
      "line_id": "01KK47CNT8J2A8A3ZZK76TY625",
      "n_cat": "anchor",
      "u_cat": "section",
      "parent_id": "01KK47CNT8TENTS25RG4WM880B",
      "dep_id": [],
      "key": "sectionPrefecture",
      "i_type": "direct",
      "f_type": "group",
      "value": ""
    },
    {
      "id": 113,
      "line_id": "01KK47CNT9X32SYETPJNEYSMT4",
      "n_cat": "line",
      "u_cat": "config",
      "parent_id": "01KK47CNT8J2A8A3ZZK76TY625",
      "dep_id": [],
      "key": "varName",
      "i_type": "direct",
      "f_type": "text",
      "value": "prefecture"
    },
    {
      "id": 114,
      "line_id": "01KK47CNT9CZSXWBVH1WD3VG0V",
      "n_cat": "line",
      "u_cat": "display",
      "parent_id": "01KK47CNT8J2A8A3ZZK76TY625",
      "dep_id": [],
      "key": "label",
      "i_type": "direct",
      "f_type": "text",
      "value": "都道府県"
    },
    {
      "id": 115,
      "line_id": "01KK47CNT9AZDBJVFTBJRH7DX1",
      "n_cat": "line",
      "u_cat": "config",
      "parent_id": "01KK47CNT8J2A8A3ZZK76TY625",
      "dep_id": [],
      "key": "order",
      "i_type": "direct",
      "f_type": "number",
      "value": 1
    },
    {
      "id": 116,
      "line_id": "01KK47CNT97HVY960NE66QX5QS",
      "n_cat": "line",
      "u_cat": "config",
      "parent_id": "01KK47CNT8J2A8A3ZZK76TY625",
      "dep_id": [],
      "key": "addBlock",
      "i_type": "direct",
      "f_type": "boolean",
      "value": ""
    },
    {
      "id": 117,
      "line_id": "01KK47CNT93WQ2E5T83AWJ0Q01",
      "n_cat": "line",
      "u_cat": "config",
      "parent_id": "01KK47CNT8J2A8A3ZZK76TY625",
      "dep_id": [],
      "key": "cpyBlock",
      "i_type": "direct",
      "f_type": "boolean",
      "value": ""
    },
    {
      "id": 118,
      "line_id": "01KK47CNT9KFWC279ZY89SHF44",
      "n_cat": "line",
      "u_cat": "config",
      "parent_id": "01KK47CNT8J2A8A3ZZK76TY625",
      "dep_id": [],
      "key": "delBlock",
      "i_type": "direct",
      "f_type": "boolean",
      "value": ""
    },
    {
      "id": 119,
      "line_id": "01KK47CNT9XCXX1PEZFKX2NA6P",
      "n_cat": "line",
      "u_cat": "config",
      "parent_id": "01KK47CNT8J2A8A3ZZK76TY625",
      "dep_id": [],
      "key": "fold",
      "i_type": "direct",
      "f_type": "boolean",
      "value": ""
    },
    {
      "id": 120,
      "line_id": "01KK47CNT9JRDAEZAWZXZJF65W",
      "n_cat": "line",
      "u_cat": "config",
      "parent_id": "01KK47CNT8J2A8A3ZZK76TY625",
      "dep_id": [],
      "key": "icon",
      "i_type": "direct",
      "f_type": "text",
      "value": ""
    },
    {
      "id": 121,
      "line_id": "01KK47CNT9Q4BARK6NJJ5KNAJV",
      "n_cat": "anchor",
      "u_cat": "field",
      "parent_id": "01KK47CNT8J2A8A3ZZK76TY625",
      "dep_id": [],
      "key": "fieldPrefecture",
      "i_type": "direct",
      "f_type": "group",
      "value": ""
    },
    {
      "id": 122,
      "line_id": "01KK47CNT9N0Y310295Z8Q7AS3",
      "n_cat": "line",
      "u_cat": "config",
      "parent_id": "01KK47CNT9Q4BARK6NJJ5KNAJV",
      "dep_id": [],
      "key": "varName",
      "i_type": "direct",
      "f_type": "text",
      "value": "prefecture"
    },
    {
      "id": 123,
      "line_id": "01KK47CNT9FBTWY81WG9CECZBE",
      "n_cat": "line",
      "u_cat": "display",
      "parent_id": "01KK47CNT9Q4BARK6NJJ5KNAJV",
      "dep_id": [],
      "key": "label",
      "i_type": "direct",
      "f_type": "text",
      "value": "都道府県"
    },
    {
      "id": 124,
      "line_id": "01KK47CNT9AA6RMSWHKG3X85D9",
      "n_cat": "line",
      "u_cat": "config",
      "parent_id": "01KK47CNT9Q4BARK6NJJ5KNAJV",
      "dep_id": [],
      "key": "order",
      "i_type": "direct",
      "f_type": "number",
      "value": 1
    },
    {
      "id": 125,
      "line_id": "01KK47CNT98XYNKY272C3ZQFNY",
      "n_cat": "line",
      "u_cat": "config",
      "parent_id": "01KK47CNT9Q4BARK6NJJ5KNAJV",
      "dep_id": [],
      "key": "addBlock",
      "i_type": "direct",
      "f_type": "boolean",
      "value": ""
    },
    {
      "id": 126,
      "line_id": "01KK47CNT9NGRHWS96Y5GK05SM",
      "n_cat": "line",
      "u_cat": "config",
      "parent_id": "01KK47CNT9Q4BARK6NJJ5KNAJV",
      "dep_id": [],
      "key": "delBlock",
      "i_type": "direct",
      "f_type": "boolean",
      "value": ""
    },
    {
      "id": 127,
      "line_id": "01KK47CNT9KPBHFCXB6X6JE43E",
      "n_cat": "line",
      "u_cat": "config",
      "parent_id": "01KK47CNT9Q4BARK6NJJ5KNAJV",
      "dep_id": [],
      "key": "cpyBlock",
      "i_type": "direct",
      "f_type": "boolean",
      "value": ""
    },
    {
      "id": 128,
      "line_id": "01KK47CNT9NVDP0BSVSPSG9S45",
      "n_cat": "line",
      "u_cat": "config",
      "parent_id": "01KK47CNT9Q4BARK6NJJ5KNAJV",
      "dep_id": [],
      "key": "required",
      "i_type": "direct",
      "f_type": "boolean",
      "value": ""
    },
    {
      "id": 129,
      "line_id": "01KK47CNT9Z36F02NRSRWJSZRC",
      "n_cat": "line",
      "u_cat": "feed",
      "parent_id": "01KK47CNT9Q4BARK6NJJ5KNAJV",
      "dep_id": [],
      "key": "hint",
      "i_type": "direct",
      "f_type": "text",
      "value": ""
    },
    {
      "id": 130,
      "line_id": "01KK47CNT9EWY9TYSKQEJAW9S3",
      "n_cat": "line",
      "u_cat": "display",
      "parent_id": "01KK47CNT9Q4BARK6NJJ5KNAJV",
      "dep_id": [],
      "key": "placeHolder",
      "i_type": "direct",
      "f_type": "text",
      "value": ""
    },
    {
      "id": 131,
      "line_id": "01KK47CNT9JK3T9ZN74WA9KPPH",
      "n_cat": "line",
      "u_cat": "display",
      "parent_id": "01KK47CNT9Q4BARK6NJJ5KNAJV",
      "dep_id": [],
      "key": "icon",
      "i_type": "direct",
      "f_type": "fa-name",
      "value": ""
    },
    {
      "id": 132,
      "line_id": "01KK47CNTA488S76QZ4CSS93Y7",
      "n_cat": "line",
      "u_cat": "config",
      "parent_id": "01KK47CNT9Q4BARK6NJJ5KNAJV",
      "dep_id": [],
      "key": "digest",
      "i_type": "direct",
      "f_type": "boolean",
      "value": true
    },
    {
      "id": 133,
      "line_id": "01KK47CNTAWE26X2C8XKG7FS9P",
      "n_cat": "line",
      "u_cat": "feed",
      "parent_id": "01KK47CNT9Q4BARK6NJJ5KNAJV",
      "dep_id": [],
      "key": "value",
      "i_type": "direct",
      "f_type": "radio",
      "value": "東京都"
    },
    {
      "id": 134,
      "line_id": "01KK47CNTAB3SNWP0RRAWVATBF",
      "n_cat": "anchor",
      "u_cat": "option",
      "parent_id": "01KK47CNTAWE26X2C8XKG7FS9P",
      "dep_id": [],
      "key": "optionPrefecture",
      "i_type": "direct",
      "f_type": "group",
      "value": ""
    },
    {
      "id": 135,
      "line_id": "01KK47CNTAK3RW50H5717BJDG2",
      "n_cat": "line",
      "u_cat": "config",
      "parent_id": "01KK47CNTAB3SNWP0RRAWVATBF",
      "dep_id": [],
      "key": "varName",
      "i_type": "direct",
      "f_type": "text",
      "value": "prefecture"
    },
    {
      "id": 136,
      "line_id": "01KK47CNTA87YM7WBZVVZGFGT9",
      "n_cat": "line",
      "u_cat": "display",
      "parent_id": "01KK47CNTAB3SNWP0RRAWVATBF",
      "dep_id": [],
      "key": "display",
      "i_type": "direct",
      "f_type": "text",
      "value": "modal"
    },
    {
      "id": 137,
      "line_id": "01KK47CNTA0MQXKSW1MV4YXV9K",
      "n_cat": "line",
      "u_cat": "config",
      "parent_id": "01KK47CNTAB3SNWP0RRAWVATBF",
      "dep_id": [],
      "key": "tableId",
      "i_type": "direct",
      "f_type": "text",
      "value": "table:prefecture_struct_[] |\r\nlineId: |\r\nkey: "
    },
    {
      "id": 138,
      "line_id": "01KK47CNTA08EGZMM5516EVV4K",
      "n_cat": "line",
      "u_cat": "config",
      "parent_id": "01KK47CNTAB3SNWP0RRAWVATBF",
      "dep_id": [],
      "key": "value",
      "i_type": "direct",
      "f_type": "text",
      "value": ""
    },
    {
      "id": 139,
      "line_id": "01KK47CNTAX1W187T0DRS3V2TS",
      "n_cat": "anchor",
      "u_cat": "section",
      "parent_id": "01KK47CNT8J2A8A3ZZK76TY625",
      "dep_id": [],
      "key": "sectionCity",
      "i_type": "direct",
      "f_type": "group",
      "value": ""
    },
    {
      "id": 140,
      "line_id": "01KK47CNTA6J6J12TEHX9P7GAE",
      "n_cat": "line",
      "u_cat": "config",
      "parent_id": "01KK47CNTAX1W187T0DRS3V2TS",
      "dep_id": [],
      "key": "varName",
      "i_type": "direct",
      "f_type": "text",
      "value": "city"
    },
    {
      "id": 141,
      "line_id": "01KK47CNTAERS3KMB7BWT6G30X",
      "n_cat": "line",
      "u_cat": "display",
      "parent_id": "01KK47CNTAX1W187T0DRS3V2TS",
      "dep_id": [],
      "key": "label",
      "i_type": "direct",
      "f_type": "text",
      "value": "市区町村"
    },
    {
      "id": 142,
      "line_id": "01KK47CNTA23GQ8VGW9GAZ65VD",
      "n_cat": "line",
      "u_cat": "config",
      "parent_id": "01KK47CNTAX1W187T0DRS3V2TS",
      "dep_id": [],
      "key": "order",
      "i_type": "direct",
      "f_type": "number",
      "value": 2
    },
    {
      "id": 143,
      "line_id": "01KK47CNTAGK2Z05W3W5PKVNNG",
      "n_cat": "line",
      "u_cat": "config",
      "parent_id": "01KK47CNTAX1W187T0DRS3V2TS",
      "dep_id": [],
      "key": "addBlock",
      "i_type": "direct",
      "f_type": "boolean",
      "value": ""
    },
    {
      "id": 144,
      "line_id": "01KK47CNTAV3RYF8F4YQCJBAN0",
      "n_cat": "line",
      "u_cat": "config",
      "parent_id": "01KK47CNTAX1W187T0DRS3V2TS",
      "dep_id": [],
      "key": "cpyBlock",
      "i_type": "direct",
      "f_type": "boolean",
      "value": ""
    },
    {
      "id": 145,
      "line_id": "01KK47CNTA7Q2M45706EHB4PE4",
      "n_cat": "line",
      "u_cat": "config",
      "parent_id": "01KK47CNTAX1W187T0DRS3V2TS",
      "dep_id": [],
      "key": "delBlock",
      "i_type": "direct",
      "f_type": "boolean",
      "value": ""
    },
    {
      "id": 146,
      "line_id": "01KK47CNTAN7TYH2D53YC1Z59H",
      "n_cat": "line",
      "u_cat": "config",
      "parent_id": "01KK47CNTAX1W187T0DRS3V2TS",
      "dep_id": [],
      "key": "fold",
      "i_type": "direct",
      "f_type": "boolean",
      "value": ""
    },
    {
      "id": 147,
      "line_id": "01KK47CNTAE5RFAJ5EPNE3W6BC",
      "n_cat": "line",
      "u_cat": "config",
      "parent_id": "01KK47CNTAX1W187T0DRS3V2TS",
      "dep_id": [],
      "key": "icon",
      "i_type": "direct",
      "f_type": "text",
      "value": ""
    },
    {
      "id": 148,
      "line_id": "01KK47CNTAN7E9JAJYX3YCTK6E",
      "n_cat": "anchor",
      "u_cat": "field",
      "parent_id": "01KK47CNTAX1W187T0DRS3V2TS",
      "dep_id": [],
      "key": "fieldCity",
      "i_type": "direct",
      "f_type": "group",
      "value": ""
    },
    {
      "id": 149,
      "line_id": "01KK47CNTA7E12B7GFP4R3ESHN",
      "n_cat": "line",
      "u_cat": "config",
      "parent_id": "01KK47CNTAN7E9JAJYX3YCTK6E",
      "dep_id": [],
      "key": "varName",
      "i_type": "direct",
      "f_type": "text",
      "value": "city"
    },
    {
      "id": 150,
      "line_id": "01KK47CNTA9YV7GPX5N7XMRMCM",
      "n_cat": "line",
      "u_cat": "display",
      "parent_id": "01KK47CNTAN7E9JAJYX3YCTK6E",
      "dep_id": [],
      "key": "label",
      "i_type": "direct",
      "f_type": "text",
      "value": "市区町村"
    },
    {
      "id": 151,
      "line_id": "01KK47CNTB50QYFC7J24CMZQFG",
      "n_cat": "line",
      "u_cat": "config",
      "parent_id": "01KK47CNTAN7E9JAJYX3YCTK6E",
      "dep_id": [],
      "key": "order",
      "i_type": "direct",
      "f_type": "number",
      "value": 1
    },
    {
      "id": 152,
      "line_id": "01KK47CNTBV0A43WSPT6R9TYFX",
      "n_cat": "line",
      "u_cat": "config",
      "parent_id": "01KK47CNTAN7E9JAJYX3YCTK6E",
      "dep_id": [],
      "key": "addBlock",
      "i_type": "direct",
      "f_type": "boolean",
      "value": ""
    },
    {
      "id": 153,
      "line_id": "01KK47CNTBNYZD7M9PFW0YTZC0",
      "n_cat": "line",
      "u_cat": "config",
      "parent_id": "01KK47CNTAN7E9JAJYX3YCTK6E",
      "dep_id": [],
      "key": "delBlock",
      "i_type": "direct",
      "f_type": "boolean",
      "value": ""
    },
    {
      "id": 154,
      "line_id": "01KK47CNTBC9J3PJP87K9XVQKT",
      "n_cat": "line",
      "u_cat": "config",
      "parent_id": "01KK47CNTAN7E9JAJYX3YCTK6E",
      "dep_id": [],
      "key": "cpyBlock",
      "i_type": "direct",
      "f_type": "boolean",
      "value": ""
    },
    {
      "id": 155,
      "line_id": "01KK47CNTBR8GN9D1SY3Q1RF46",
      "n_cat": "line",
      "u_cat": "config",
      "parent_id": "01KK47CNTAN7E9JAJYX3YCTK6E",
      "dep_id": [],
      "key": "required",
      "i_type": "direct",
      "f_type": "boolean",
      "value": ""
    },
    {
      "id": 156,
      "line_id": "01KK47CNTB0EEFHT2R76H7G216",
      "n_cat": "line",
      "u_cat": "feed",
      "parent_id": "01KK47CNTAN7E9JAJYX3YCTK6E",
      "dep_id": [],
      "key": "hint",
      "i_type": "direct",
      "f_type": "text",
      "value": ""
    },
    {
      "id": 157,
      "line_id": "01KK47CNTBXS2ANM4G9XA5PKZY",
      "n_cat": "line",
      "u_cat": "display",
      "parent_id": "01KK47CNTAN7E9JAJYX3YCTK6E",
      "dep_id": [],
      "key": "placeHolder",
      "i_type": "direct",
      "f_type": "text",
      "value": ""
    },
    {
      "id": 158,
      "line_id": "01KK47CNTBDXREFWN9HHQMNF1K",
      "n_cat": "line",
      "u_cat": "display",
      "parent_id": "01KK47CNTAN7E9JAJYX3YCTK6E",
      "dep_id": [],
      "key": "icon",
      "i_type": "direct",
      "f_type": "fa-name",
      "value": ""
    },
    {
      "id": 159,
      "line_id": "01KK47CNTBZEB19NRYVWB2RSYD",
      "n_cat": "line",
      "u_cat": "config",
      "parent_id": "01KK47CNTAN7E9JAJYX3YCTK6E",
      "dep_id": [],
      "key": "digest",
      "i_type": "direct",
      "f_type": "boolean",
      "value": true
    },
    {
      "id": 160,
      "line_id": "01KK47CNTBA723F6NJ2T13WZ9X",
      "n_cat": "line",
      "u_cat": "feed",
      "parent_id": "01KK47CNTAN7E9JAJYX3YCTK6E",
      "dep_id": [],
      "key": "value",
      "i_type": "direct",
      "f_type": "radio",
      "value": "文京区"
    },
    {
      "id": 161,
      "line_id": "01KK47CNTB4FVRHSKQSWWKQMBD",
      "n_cat": "anchor",
      "u_cat": "option",
      "parent_id": "01KK47CNTBA723F6NJ2T13WZ9X",
      "dep_id": [],
      "key": "optionCity",
      "i_type": "direct",
      "f_type": "group",
      "value": ""
    },
    {
      "id": 162,
      "line_id": "01KK47CNTBBP044NV8QJE3YR56",
      "n_cat": "line",
      "u_cat": "config",
      "parent_id": "01KK47CNTB4FVRHSKQSWWKQMBD",
      "dep_id": [],
      "key": "varName",
      "i_type": "direct",
      "f_type": "text",
      "value": "city"
    },
    {
      "id": 163,
      "line_id": "01KK47CNTBAP3CYN51FM7ZK4GW",
      "n_cat": "line",
      "u_cat": "display",
      "parent_id": "01KK47CNTB4FVRHSKQSWWKQMBD",
      "dep_id": [],
      "key": "display",
      "i_type": "direct",
      "f_type": "text",
      "value": "modal"
    },
    {
      "id": 164,
      "line_id": "01KK47CNTB2GSEKMHRV1ZZDQMN",
      "n_cat": "line",
      "u_cat": "config",
      "parent_id": "01KK47CNTB4FVRHSKQSWWKQMBD",
      "dep_id": [],
      "key": "tableId",
      "i_type": "direct",
      "f_type": "text",
      "value": "table:city_struct_[] |\r\nlineId: |\r\nkey: "
    },
    {
      "id": 165,
      "line_id": "01KK47CNTBC776G77PN9RK3WMH",
      "n_cat": "line",
      "u_cat": "config",
      "parent_id": "01KK47CNTB4FVRHSKQSWWKQMBD",
      "dep_id": [],
      "key": "value",
      "i_type": "direct",
      "f_type": "text",
      "value": ""
    },
    {
      "id": 166,
      "line_id": "01KK47CNTBSZZ22B8JBCFDEDPM",
      "n_cat": "anchor",
      "u_cat": "section",
      "parent_id": "01KK47CNT3EERBQTYH7ENFNBVS",
      "dep_id": [],
      "key": "sectionOfficeAddress",
      "i_type": "direct",
      "f_type": "group",
      "value": ""
    },
    {
      "id": 167,
      "line_id": "01KK47CNTBVZ91BRYBAN1RFKD1",
      "n_cat": "line",
      "u_cat": "config",
      "parent_id": "01KK47CNTBSZZ22B8JBCFDEDPM",
      "dep_id": [],
      "key": "varName",
      "i_type": "direct",
      "f_type": "text",
      "value": "officeAddress"
    },
    {
      "id": 168,
      "line_id": "01KK47CNTBK0CPH6836KEGQPG0",
      "n_cat": "line",
      "u_cat": "display",
      "parent_id": "01KK47CNTBSZZ22B8JBCFDEDPM",
      "dep_id": [],
      "key": "label",
      "i_type": "direct",
      "f_type": "text",
      "value": "勤務先住所"
    },
    {
      "id": 169,
      "line_id": "01KK47CNTC0DCG204EM30Z9GF7",
      "n_cat": "line",
      "u_cat": "config",
      "parent_id": "01KK47CNTBSZZ22B8JBCFDEDPM",
      "dep_id": [],
      "key": "order",
      "i_type": "direct",
      "f_type": "number",
      "value": 4
    },
    {
      "id": 170,
      "line_id": "01KK47CNTC7YB5JMCN9REPKZSZ",
      "n_cat": "line",
      "u_cat": "config",
      "parent_id": "01KK47CNTBSZZ22B8JBCFDEDPM",
      "dep_id": [],
      "key": "addBlock",
      "i_type": "direct",
      "f_type": "boolean",
      "value": ""
    },
    {
      "id": 171,
      "line_id": "01KK47CNTCTFCB2D9VMP0265ES",
      "n_cat": "line",
      "u_cat": "config",
      "parent_id": "01KK47CNTBSZZ22B8JBCFDEDPM",
      "dep_id": [],
      "key": "cpyBlock",
      "i_type": "direct",
      "f_type": "boolean",
      "value": ""
    },
    {
      "id": 172,
      "line_id": "01KK47CNTC67P4H52X5G2VKGR2",
      "n_cat": "line",
      "u_cat": "config",
      "parent_id": "01KK47CNTBSZZ22B8JBCFDEDPM",
      "dep_id": [],
      "key": "delBlock",
      "i_type": "direct",
      "f_type": "boolean",
      "value": ""
    },
    {
      "id": 173,
      "line_id": "01KK47CNTCEW5BDVAG1X77X074",
      "n_cat": "line",
      "u_cat": "config",
      "parent_id": "01KK47CNTBSZZ22B8JBCFDEDPM",
      "dep_id": [],
      "key": "fold",
      "i_type": "direct",
      "f_type": "boolean",
      "value": ""
    },
    {
      "id": 174,
      "line_id": "01KK47CNTCE3SMEASQCZPXFGD3",
      "n_cat": "line",
      "u_cat": "config",
      "parent_id": "01KK47CNTBSZZ22B8JBCFDEDPM",
      "dep_id": [],
      "key": "icon",
      "i_type": "direct",
      "f_type": "text",
      "value": ""
    },
    {
      "id": 175,
      "line_id": "01KK47CNTC5MA6Y1D2V5JY903W",
      "n_cat": "anchor",
      "u_cat": "section",
      "parent_id": "01KK47CNTBSZZ22B8JBCFDEDPM",
      "dep_id": [],
      "key": "sectionPrefecture",
      "i_type": "direct",
      "f_type": "group",
      "value": ""
    },
    {
      "id": 176,
      "line_id": "01KK47CNTCEDYGYEW9FNRA4AAQ",
      "n_cat": "line",
      "u_cat": "config",
      "parent_id": "01KK47CNTC5MA6Y1D2V5JY903W",
      "dep_id": [],
      "key": "varName",
      "i_type": "direct",
      "f_type": "text",
      "value": "prefecture"
    },
    {
      "id": 177,
      "line_id": "01KK47CNTCYH32R8R41KZ3H34V",
      "n_cat": "line",
      "u_cat": "display",
      "parent_id": "01KK47CNTC5MA6Y1D2V5JY903W",
      "dep_id": [],
      "key": "label",
      "i_type": "direct",
      "f_type": "text",
      "value": "都道府県"
    },
    {
      "id": 178,
      "line_id": "01KK47CNTCGF6KAGQGSVWWV3CY",
      "n_cat": "line",
      "u_cat": "config",
      "parent_id": "01KK47CNTC5MA6Y1D2V5JY903W",
      "dep_id": [],
      "key": "order",
      "i_type": "direct",
      "f_type": "number",
      "value": 1
    },
    {
      "id": 179,
      "line_id": "01KK47CNTCKS8VYF92W1P02WJG",
      "n_cat": "line",
      "u_cat": "config",
      "parent_id": "01KK47CNTC5MA6Y1D2V5JY903W",
      "dep_id": [],
      "key": "addBlock",
      "i_type": "direct",
      "f_type": "boolean",
      "value": ""
    },
    {
      "id": 180,
      "line_id": "01KK47CNTCKV5M0VRVVN1DRHKE",
      "n_cat": "line",
      "u_cat": "config",
      "parent_id": "01KK47CNTC5MA6Y1D2V5JY903W",
      "dep_id": [],
      "key": "cpyBlock",
      "i_type": "direct",
      "f_type": "boolean",
      "value": ""
    },
    {
      "id": 181,
      "line_id": "01KK47CNTC8B2603CHT16YP812",
      "n_cat": "line",
      "u_cat": "config",
      "parent_id": "01KK47CNTC5MA6Y1D2V5JY903W",
      "dep_id": [],
      "key": "delBlock",
      "i_type": "direct",
      "f_type": "boolean",
      "value": ""
    },
    {
      "id": 182,
      "line_id": "01KK47CNTCQY0JS2XCJ8VXP2RM",
      "n_cat": "line",
      "u_cat": "config",
      "parent_id": "01KK47CNTC5MA6Y1D2V5JY903W",
      "dep_id": [],
      "key": "fold",
      "i_type": "direct",
      "f_type": "boolean",
      "value": ""
    },
    {
      "id": 183,
      "line_id": "01KK47CNTCJB4C4E2VAS8Y00ME",
      "n_cat": "line",
      "u_cat": "config",
      "parent_id": "01KK47CNTC5MA6Y1D2V5JY903W",
      "dep_id": [],
      "key": "icon",
      "i_type": "direct",
      "f_type": "text",
      "value": ""
    },
    {
      "id": 184,
      "line_id": "01KK47CNTCQHSP9A6EX22NP5HD",
      "n_cat": "anchor",
      "u_cat": "field",
      "parent_id": "01KK47CNTC5MA6Y1D2V5JY903W",
      "dep_id": [],
      "key": "fieldPrefecture",
      "i_type": "direct",
      "f_type": "group",
      "value": ""
    },
    {
      "id": 185,
      "line_id": "01KK47CNTCJ710GJ1XHSV59YH4",
      "n_cat": "line",
      "u_cat": "config",
      "parent_id": "01KK47CNTCQHSP9A6EX22NP5HD",
      "dep_id": [],
      "key": "varName",
      "i_type": "direct",
      "f_type": "text",
      "value": "prefecture"
    },
    {
      "id": 186,
      "line_id": "01KK47CNTCAY1SFXR0WG7K4W88",
      "n_cat": "line",
      "u_cat": "display",
      "parent_id": "01KK47CNTCQHSP9A6EX22NP5HD",
      "dep_id": [],
      "key": "label",
      "i_type": "direct",
      "f_type": "text",
      "value": "都道府県"
    },
    {
      "id": 187,
      "line_id": "01KK47CNTCDGYPHG0GDACB14VQ",
      "n_cat": "line",
      "u_cat": "config",
      "parent_id": "01KK47CNTCQHSP9A6EX22NP5HD",
      "dep_id": [],
      "key": "order",
      "i_type": "direct",
      "f_type": "number",
      "value": 1
    },
    {
      "id": 188,
      "line_id": "01KK47CNTD0J5N7RRXT3NEWCPX",
      "n_cat": "line",
      "u_cat": "config",
      "parent_id": "01KK47CNTCQHSP9A6EX22NP5HD",
      "dep_id": [],
      "key": "addBlock",
      "i_type": "direct",
      "f_type": "boolean",
      "value": ""
    },
    {
      "id": 189,
      "line_id": "01KK47CNTDS9HQPCT6CWFFAYXG",
      "n_cat": "line",
      "u_cat": "config",
      "parent_id": "01KK47CNTCQHSP9A6EX22NP5HD",
      "dep_id": [],
      "key": "delBlock",
      "i_type": "direct",
      "f_type": "boolean",
      "value": ""
    },
    {
      "id": 190,
      "line_id": "01KK47CNTDFEBNDGW3NRKQHR57",
      "n_cat": "line",
      "u_cat": "config",
      "parent_id": "01KK47CNTCQHSP9A6EX22NP5HD",
      "dep_id": [],
      "key": "cpyBlock",
      "i_type": "direct",
      "f_type": "boolean",
      "value": ""
    },
    {
      "id": 191,
      "line_id": "01KK47CNTDX2GH9KC0E6NRT7ZZ",
      "n_cat": "line",
      "u_cat": "config",
      "parent_id": "01KK47CNTCQHSP9A6EX22NP5HD",
      "dep_id": [],
      "key": "required",
      "i_type": "direct",
      "f_type": "boolean",
      "value": ""
    },
    {
      "id": 192,
      "line_id": "01KK47CNTDPD8BNTNGPB40K42F",
      "n_cat": "line",
      "u_cat": "feed",
      "parent_id": "01KK47CNTCQHSP9A6EX22NP5HD",
      "dep_id": [],
      "key": "hint",
      "i_type": "direct",
      "f_type": "text",
      "value": ""
    },
    {
      "id": 193,
      "line_id": "01KK47CNTDCA2JE7AN87YZN7SP",
      "n_cat": "line",
      "u_cat": "display",
      "parent_id": "01KK47CNTCQHSP9A6EX22NP5HD",
      "dep_id": [],
      "key": "placeHolder",
      "i_type": "direct",
      "f_type": "text",
      "value": ""
    },
    {
      "id": 194,
      "line_id": "01KK47CNTD8RDHZC12HV5FV1QQ",
      "n_cat": "line",
      "u_cat": "display",
      "parent_id": "01KK47CNTCQHSP9A6EX22NP5HD",
      "dep_id": [],
      "key": "icon",
      "i_type": "direct",
      "f_type": "fa-name",
      "value": ""
    },
    {
      "id": 195,
      "line_id": "01KK47CNTD4Z8HN421DXB61K8P",
      "n_cat": "line",
      "u_cat": "config",
      "parent_id": "01KK47CNTCQHSP9A6EX22NP5HD",
      "dep_id": [],
      "key": "digest",
      "i_type": "direct",
      "f_type": "boolean",
      "value": true
    },
    {
      "id": 196,
      "line_id": "01KK47CNTDYNGC8S9AXCBCE6S6",
      "n_cat": "line",
      "u_cat": "feed",
      "parent_id": "01KK47CNTCQHSP9A6EX22NP5HD",
      "dep_id": [],
      "key": "value",
      "i_type": "direct",
      "f_type": "radio",
      "value": "神奈川県"
    },
    {
      "id": 197,
      "line_id": "01KK47CNTDSQ6VEC4CB4P4RTBM",
      "n_cat": "anchor",
      "u_cat": "option",
      "parent_id": "01KK47CNTDYNGC8S9AXCBCE6S6",
      "dep_id": [],
      "key": "optionPrefecture",
      "i_type": "direct",
      "f_type": "group",
      "value": ""
    },
    {
      "id": 198,
      "line_id": "01KK47CNTD6BSWN9E82P3KGBQ3",
      "n_cat": "line",
      "u_cat": "config",
      "parent_id": "01KK47CNTDSQ6VEC4CB4P4RTBM",
      "dep_id": [],
      "key": "varName",
      "i_type": "direct",
      "f_type": "text",
      "value": "prefecture"
    },
    {
      "id": 199,
      "line_id": "01KK47CNTDFG4SD1WW2K7C4WST",
      "n_cat": "line",
      "u_cat": "display",
      "parent_id": "01KK47CNTDSQ6VEC4CB4P4RTBM",
      "dep_id": [],
      "key": "display",
      "i_type": "direct",
      "f_type": "text",
      "value": "modal"
    },
    {
      "id": 200,
      "line_id": "01KK47CNTDN0EXNZV5G9EKH3G7",
      "n_cat": "line",
      "u_cat": "config",
      "parent_id": "01KK47CNTDSQ6VEC4CB4P4RTBM",
      "dep_id": [],
      "key": "tableId",
      "i_type": "direct",
      "f_type": "text",
      "value": "table:prefecture_struct_[] |\r\nlineId: |\r\nkey: "
    },
    {
      "id": 201,
      "line_id": "01KK47CNTDBN1SBM6T0GRW55ZV",
      "n_cat": "line",
      "u_cat": "config",
      "parent_id": "01KK47CNTDSQ6VEC4CB4P4RTBM",
      "dep_id": [],
      "key": "value",
      "i_type": "direct",
      "f_type": "text",
      "value": ""
    },
    {
      "id": 202,
      "line_id": "01KK47CNTDW6CMTF08CTHMVWS1",
      "n_cat": "anchor",
      "u_cat": "section",
      "parent_id": "01KK47CNTC5MA6Y1D2V5JY903W",
      "dep_id": [],
      "key": "sectionCity",
      "i_type": "direct",
      "f_type": "group",
      "value": ""
    },
    {
      "id": 203,
      "line_id": "01KK47CNTDTVGV0Q2TY87EC2PG",
      "n_cat": "line",
      "u_cat": "config",
      "parent_id": "01KK47CNTDW6CMTF08CTHMVWS1",
      "dep_id": [],
      "key": "varName",
      "i_type": "direct",
      "f_type": "text",
      "value": "city"
    },
    {
      "id": 204,
      "line_id": "01KK47CNTDFM8TRCX3MSXJ3AD3",
      "n_cat": "line",
      "u_cat": "display",
      "parent_id": "01KK47CNTDW6CMTF08CTHMVWS1",
      "dep_id": [],
      "key": "label",
      "i_type": "direct",
      "f_type": "text",
      "value": "市区町村"
    },
    {
      "id": 205,
      "line_id": "01KK47CNTD7JPV0Y1GJ8Y4AFCD",
      "n_cat": "line",
      "u_cat": "config",
      "parent_id": "01KK47CNTDW6CMTF08CTHMVWS1",
      "dep_id": [],
      "key": "order",
      "i_type": "direct",
      "f_type": "number",
      "value": 2
    },
    {
      "id": 206,
      "line_id": "01KK47CNTD4793WCD1WTHQ0W8W",
      "n_cat": "line",
      "u_cat": "config",
      "parent_id": "01KK47CNTDW6CMTF08CTHMVWS1",
      "dep_id": [],
      "key": "addBlock",
      "i_type": "direct",
      "f_type": "boolean",
      "value": ""
    },
    {
      "id": 207,
      "line_id": "01KK47CNTES1A6NPGN7ZA02GVV",
      "n_cat": "line",
      "u_cat": "config",
      "parent_id": "01KK47CNTDW6CMTF08CTHMVWS1",
      "dep_id": [],
      "key": "cpyBlock",
      "i_type": "direct",
      "f_type": "boolean",
      "value": ""
    },
    {
      "id": 208,
      "line_id": "01KK47CNTEM27MM50EBAZS8H5E",
      "n_cat": "line",
      "u_cat": "config",
      "parent_id": "01KK47CNTDW6CMTF08CTHMVWS1",
      "dep_id": [],
      "key": "delBlock",
      "i_type": "direct",
      "f_type": "boolean",
      "value": ""
    },
    {
      "id": 209,
      "line_id": "01KK47CNTEW4593XA5R6C8NT1D",
      "n_cat": "line",
      "u_cat": "config",
      "parent_id": "01KK47CNTDW6CMTF08CTHMVWS1",
      "dep_id": [],
      "key": "fold",
      "i_type": "direct",
      "f_type": "boolean",
      "value": ""
    },
    {
      "id": 210,
      "line_id": "01KK47CNTEK82Y0R2Y8QJ0YTD8",
      "n_cat": "line",
      "u_cat": "config",
      "parent_id": "01KK47CNTDW6CMTF08CTHMVWS1",
      "dep_id": [],
      "key": "icon",
      "i_type": "direct",
      "f_type": "text",
      "value": ""
    },
    {
      "id": 211,
      "line_id": "01KK47CNTEN9DNYBXDK37AT591",
      "n_cat": "anchor",
      "u_cat": "field",
      "parent_id": "01KK47CNTDW6CMTF08CTHMVWS1",
      "dep_id": [],
      "key": "fieldCity",
      "i_type": "direct",
      "f_type": "group",
      "value": ""
    },
    {
      "id": 212,
      "line_id": "01KK47CNTE1P67355MT8YZ6FD8",
      "n_cat": "line",
      "u_cat": "config",
      "parent_id": "01KK47CNTEN9DNYBXDK37AT591",
      "dep_id": [],
      "key": "varName",
      "i_type": "direct",
      "f_type": "text",
      "value": "city"
    },
    {
      "id": 213,
      "line_id": "01KK47CNTE1XE77AKPTWKHJPGY",
      "n_cat": "line",
      "u_cat": "display",
      "parent_id": "01KK47CNTEN9DNYBXDK37AT591",
      "dep_id": [],
      "key": "label",
      "i_type": "direct",
      "f_type": "text",
      "value": "市区町村"
    },
    {
      "id": 214,
      "line_id": "01KK47CNTE4V3VKN4PK3G4RSVE",
      "n_cat": "line",
      "u_cat": "config",
      "parent_id": "01KK47CNTEN9DNYBXDK37AT591",
      "dep_id": [],
      "key": "order",
      "i_type": "direct",
      "f_type": "number",
      "value": 1
    },
    {
      "id": 215,
      "line_id": "01KK47CNTE497MZ2WM9F65C7E8",
      "n_cat": "line",
      "u_cat": "config",
      "parent_id": "01KK47CNTEN9DNYBXDK37AT591",
      "dep_id": [],
      "key": "addBlock",
      "i_type": "direct",
      "f_type": "boolean",
      "value": ""
    },
    {
      "id": 216,
      "line_id": "01KK47CNTEQEAQ3AWFQEZ6QPBE",
      "n_cat": "line",
      "u_cat": "config",
      "parent_id": "01KK47CNTEN9DNYBXDK37AT591",
      "dep_id": [],
      "key": "delBlock",
      "i_type": "direct",
      "f_type": "boolean",
      "value": ""
    },
    {
      "id": 217,
      "line_id": "01KK47CNTEV9PA3M9GXN2F3H8V",
      "n_cat": "line",
      "u_cat": "config",
      "parent_id": "01KK47CNTEN9DNYBXDK37AT591",
      "dep_id": [],
      "key": "cpyBlock",
      "i_type": "direct",
      "f_type": "boolean",
      "value": ""
    },
    {
      "id": 218,
      "line_id": "01KK47CNTEFSYKRRW7Z9C9ZVRF",
      "n_cat": "line",
      "u_cat": "config",
      "parent_id": "01KK47CNTEN9DNYBXDK37AT591",
      "dep_id": [],
      "key": "required",
      "i_type": "direct",
      "f_type": "boolean",
      "value": ""
    },
    {
      "id": 219,
      "line_id": "01KK47CNTEMJQ8ZD660GF1JGF6",
      "n_cat": "line",
      "u_cat": "feed",
      "parent_id": "01KK47CNTEN9DNYBXDK37AT591",
      "dep_id": [],
      "key": "hint",
      "i_type": "direct",
      "f_type": "text",
      "value": ""
    },
    {
      "id": 220,
      "line_id": "01KK47CNTE3J5MQ91BHT39T6P2",
      "n_cat": "line",
      "u_cat": "display",
      "parent_id": "01KK47CNTEN9DNYBXDK37AT591",
      "dep_id": [],
      "key": "placeHolder",
      "i_type": "direct",
      "f_type": "text",
      "value": ""
    },
    {
      "id": 221,
      "line_id": "01KK47CNTEXSVJ75K0A7043KC5",
      "n_cat": "line",
      "u_cat": "display",
      "parent_id": "01KK47CNTEN9DNYBXDK37AT591",
      "dep_id": [],
      "key": "icon",
      "i_type": "direct",
      "f_type": "fa-name",
      "value": ""
    },
    {
      "id": 222,
      "line_id": "01KK47CNTE7ZMNWQ6PH14KVZ4T",
      "n_cat": "line",
      "u_cat": "config",
      "parent_id": "01KK47CNTEN9DNYBXDK37AT591",
      "dep_id": [],
      "key": "digest",
      "i_type": "direct",
      "f_type": "boolean",
      "value": true
    },
    {
      "id": 223,
      "line_id": "01KK47CNTEWW2GZ5GQ3XNRJVH8",
      "n_cat": "line",
      "u_cat": "feed",
      "parent_id": "01KK47CNTEN9DNYBXDK37AT591",
      "dep_id": [],
      "key": "value",
      "i_type": "direct",
      "f_type": "radio",
      "value": "横浜市"
    },
    {
      "id": 224,
      "line_id": "01KK47CNTE1Q374MPK5YJM2F0J",
      "n_cat": "anchor",
      "u_cat": "option",
      "parent_id": "01KK47CNTEWW2GZ5GQ3XNRJVH8",
      "dep_id": [],
      "key": "optionCity",
      "i_type": "direct",
      "f_type": "group",
      "value": ""
    },
    {
      "id": 225,
      "line_id": "01KK47CNTFREGZ1X9PDKDKP0EC",
      "n_cat": "line",
      "u_cat": "config",
      "parent_id": "01KK47CNTE1Q374MPK5YJM2F0J",
      "dep_id": [],
      "key": "varName",
      "i_type": "direct",
      "f_type": "text",
      "value": "city"
    },
    {
      "id": 226,
      "line_id": "01KK47CNTF5Z2ZGNBPB9N13NHJ",
      "n_cat": "line",
      "u_cat": "display",
      "parent_id": "01KK47CNTE1Q374MPK5YJM2F0J",
      "dep_id": [],
      "key": "display",
      "i_type": "direct",
      "f_type": "text",
      "value": "modal"
    },
    {
      "id": 227,
      "line_id": "01KK47CNTFBRGJPTNTFSE22TV9",
      "n_cat": "line",
      "u_cat": "config",
      "parent_id": "01KK47CNTE1Q374MPK5YJM2F0J",
      "dep_id": [],
      "key": "tableId",
      "i_type": "direct",
      "f_type": "text",
      "value": "table:city_struct_[] |\r\nlineId: |\r\nkey: "
    },
    {
      "id": 228,
      "line_id": "01KK47CNTFWX84XXMEJVXXDQ81",
      "n_cat": "line",
      "u_cat": "config",
      "parent_id": "01KK47CNTE1Q374MPK5YJM2F0J",
      "dep_id": [],
      "key": "value",
      "i_type": "direct",
      "f_type": "text",
      "value": ""
    },
    {
      "id": 229,
      "line_id": "01KK47CNTFKA90XDVV8TS7MATB",
      "n_cat": "anchor",
      "u_cat": "section",
      "parent_id": "01KK47CNT3EERBQTYH7ENFNBVS",
      "dep_id": [],
      "key": "sectionSalary",
      "i_type": "direct",
      "f_type": "group",
      "value": ""
    },
    {
      "id": 230,
      "line_id": "01KK47CNTF1R8BQAY9GE51D4R9",
      "n_cat": "line",
      "u_cat": "config",
      "parent_id": "01KK47CNTFKA90XDVV8TS7MATB",
      "dep_id": [],
      "key": "varName",
      "i_type": "direct",
      "f_type": "text",
      "value": "salary"
    },
    {
      "id": 231,
      "line_id": "01KK47CNTF72Q307X95J76JY1F",
      "n_cat": "line",
      "u_cat": "display",
      "parent_id": "01KK47CNTFKA90XDVV8TS7MATB",
      "dep_id": [],
      "key": "label",
      "i_type": "direct",
      "f_type": "text",
      "value": "単金"
    },
    {
      "id": 232,
      "line_id": "01KK47CNTFSK0CRBREMF5PJ23A",
      "n_cat": "line",
      "u_cat": "config",
      "parent_id": "01KK47CNTFKA90XDVV8TS7MATB",
      "dep_id": [],
      "key": "order",
      "i_type": "direct",
      "f_type": "number",
      "value": 5
    },
    {
      "id": 233,
      "line_id": "01KK47CNTF5ME717KDY1W7VMFX",
      "n_cat": "line",
      "u_cat": "config",
      "parent_id": "01KK47CNTFKA90XDVV8TS7MATB",
      "dep_id": [],
      "key": "addBlock",
      "i_type": "direct",
      "f_type": "boolean",
      "value": true
    },
    {
      "id": 234,
      "line_id": "01KK47CNTFGC5BPPBWKYFRKQ60",
      "n_cat": "line",
      "u_cat": "config",
      "parent_id": "01KK47CNTFKA90XDVV8TS7MATB",
      "dep_id": [],
      "key": "cpyBlock",
      "i_type": "direct",
      "f_type": "boolean",
      "value": ""
    },
    {
      "id": 235,
      "line_id": "01KK47CNTFWVGRCSJ1B05GQE2T",
      "n_cat": "line",
      "u_cat": "config",
      "parent_id": "01KK47CNTFKA90XDVV8TS7MATB",
      "dep_id": [],
      "key": "delBlock",
      "i_type": "direct",
      "f_type": "boolean",
      "value": ""
    },
    {
      "id": 236,
      "line_id": "01KK47CNTFX8NXV2X1NHTGEEFB",
      "n_cat": "line",
      "u_cat": "config",
      "parent_id": "01KK47CNTFKA90XDVV8TS7MATB",
      "dep_id": [],
      "key": "fold",
      "i_type": "direct",
      "f_type": "boolean",
      "value": ""
    },
    {
      "id": 237,
      "line_id": "01KK47CNTF83DX8V4DYHYG8TEY",
      "n_cat": "line",
      "u_cat": "config",
      "parent_id": "01KK47CNTFKA90XDVV8TS7MATB",
      "dep_id": [],
      "key": "icon",
      "i_type": "direct",
      "f_type": "text",
      "value": ""
    },
    {
      "id": 238,
      "line_id": "01KK47CNTF6A0GBKRR854PP5X6",
      "n_cat": "anchor",
      "u_cat": "field",
      "parent_id": "01KK47CNTFKA90XDVV8TS7MATB",
      "dep_id": [],
      "key": "fieldSalary",
      "i_type": "direct",
      "f_type": "group",
      "value": ""
    },
    {
      "id": 239,
      "line_id": "01KK47CNTF43GPMC22Q3C0741G",
      "n_cat": "line",
      "u_cat": "config",
      "parent_id": "01KK47CNTF6A0GBKRR854PP5X6",
      "dep_id": [],
      "key": "varName",
      "i_type": "direct",
      "f_type": "text",
      "value": "salary"
    },
    {
      "id": 240,
      "line_id": "01KK47CNTF117TZQDBHCBGXXT1",
      "n_cat": "line",
      "u_cat": "display",
      "parent_id": "01KK47CNTF6A0GBKRR854PP5X6",
      "dep_id": [],
      "key": "label",
      "i_type": "direct",
      "f_type": "text",
      "value": "単金"
    },
    {
      "id": 241,
      "line_id": "01KK47CNTGVGZD5HNMCSVY2026",
      "n_cat": "line",
      "u_cat": "config",
      "parent_id": "01KK47CNTF6A0GBKRR854PP5X6",
      "dep_id": [],
      "key": "order",
      "i_type": "direct",
      "f_type": "number",
      "value": 1
    },
    {
      "id": 242,
      "line_id": "01KK47CNTGV2KGXKJ8T8ZR9YY4",
      "n_cat": "line",
      "u_cat": "config",
      "parent_id": "01KK47CNTF6A0GBKRR854PP5X6",
      "dep_id": [],
      "key": "addBlock",
      "i_type": "direct",
      "f_type": "boolean",
      "value": ""
    },
    {
      "id": 243,
      "line_id": "01KK47CNTGETCFS7014AYXN4RY",
      "n_cat": "line",
      "u_cat": "config",
      "parent_id": "01KK47CNTF6A0GBKRR854PP5X6",
      "dep_id": [],
      "key": "delBlock",
      "i_type": "direct",
      "f_type": "boolean",
      "value": true
    },
    {
      "id": 244,
      "line_id": "01KK47CNTG41R7798H7JHVVFS1",
      "n_cat": "line",
      "u_cat": "config",
      "parent_id": "01KK47CNTF6A0GBKRR854PP5X6",
      "dep_id": [],
      "key": "cpyBlock",
      "i_type": "direct",
      "f_type": "boolean",
      "value": ""
    },
    {
      "id": 245,
      "line_id": "01KK47CNTG1T5F34N16QSW1Q9B",
      "n_cat": "line",
      "u_cat": "config",
      "parent_id": "01KK47CNTF6A0GBKRR854PP5X6",
      "dep_id": [],
      "key": "required",
      "i_type": "direct",
      "f_type": "boolean",
      "value": true
    },
    {
      "id": 246,
      "line_id": "01KK47CNTG73RW17R15S9XJ3EE",
      "n_cat": "line",
      "u_cat": "feed",
      "parent_id": "01KK47CNTF6A0GBKRR854PP5X6",
      "dep_id": [],
      "key": "hint",
      "i_type": "direct",
      "f_type": "text",
      "value": ""
    },
    {
      "id": 247,
      "line_id": "01KK47CNTGCJGE941HNV8BDZRZ",
      "n_cat": "line",
      "u_cat": "display",
      "parent_id": "01KK47CNTF6A0GBKRR854PP5X6",
      "dep_id": [],
      "key": "placeHolder",
      "i_type": "direct",
      "f_type": "text",
      "value": "単金を入力してください"
    },
    {
      "id": 248,
      "line_id": "01KK47CNTGMGZ3CPX1AREGSXRK",
      "n_cat": "line",
      "u_cat": "display",
      "parent_id": "01KK47CNTF6A0GBKRR854PP5X6",
      "dep_id": [],
      "key": "icon",
      "i_type": "direct",
      "f_type": "fa-name",
      "value": ""
    },
    {
      "id": 249,
      "line_id": "01KK47CNTG1RNJ2NV6FG3FV27B",
      "n_cat": "line",
      "u_cat": "config",
      "parent_id": "01KK47CNTF6A0GBKRR854PP5X6",
      "dep_id": [],
      "key": "digest",
      "i_type": "direct",
      "f_type": "boolean",
      "value": true
    },
    {
      "id": 250,
      "line_id": "01KK47CNTG2S63YFYMNJFHMZ8K",
      "n_cat": "line",
      "u_cat": "feed",
      "parent_id": "01KK47CNTF6A0GBKRR854PP5X6",
      "dep_id": [],
      "key": "value",
      "i_type": "direct",
      "f_type": "text",
      "value": "50万円"
    }
  ]
}